apiquotamanager/__init__.py
apiquotamanager/taleo_quota_manager.py
apiquotamanager-0.0.1.dist-info/LICENSE.txt
apiquotamanager-0.0.1.dist-info/METADATA
apiquotamanager-0.0.1.dist-info/WHEEL
apiquotamanager-0.0.1.dist-info/top_level.txt
apiquotamanager-0.0.1.dist-info/RECORD
