Metadata-Version: 2.1
Name: apiquotamanager
Version: 0.0.1
Summary: API Quota Manager Python
Author: Sunny Dung
Author-email: sdung@jobsync.com
Classifier: Programming Language :: Python :: 3
Classifier: License :: OSI Approved :: MIT License
Classifier: Operating System :: OS Independent
Requires-Python: >=3.8
License-File: LICENSE.txt
